{
    "name": "Förderbereiche",
    "children": 
 [
      {
        "name":"Verhinderung des Einstiegs",
        "size":32733078
      },
      {
        "name":"Förderung des Ausstiegs",
        "size":51819450
      },
      {
        "name":"Schutz vor Passivrauchen",
        "size":9897361
      },
      {
        "name":"Sensibilisierung und Info Öffentlichkeit",
        "size":52671727
      },
      {
        "name":"Förderung Forschung",
        "size":26461988
      },
      {
        "name":"präventionsunterstützender Rahmenbedingungen",
        "size":10808512
      },
      {
        "name":"Kantonales Programm",
        "size":14265051
      }
 ]
}
